Workbook

Sheet Cover
A1: Croda International — Valuation Model
A2: LON: CRDA · Specialty Chemicals — Life Sciences · built by Sanjeeban Sumans, June 2026
A4: What's in here
A5: Assumptions holds every input the model runs on. Change a number here and everything downstream updates with it.
A6: Income Statement, Balance Sheet and Cash Flow are the three statements, built off Croda's own FY2025 results where actuals exist.
A7: DCF discounts the unlevered cash flow at WACC, with a sensitivity grid so the answer isn't pinned to one assumption.
A8: Comps checks the DCF against three peers.
A9: Summary is the football field: the one page that shows where all four methods land relative to today's price.
A13: Headline output
A14: Current share price (26 Jun 2026) | B14: 3107
A15: DCF implied value per share (base case) | B15: =DCF!B27 -> 2741.1422
A16: Comps-implied value per share (peer P/E) | B16: =Comps!J12 -> 3841.0147
A18: Source note
A19: Historical figures are sourced from Croda International's FY2025 Results, Finance Review 2025, and Q1 2026 Trading Update (all croda.com),
A20: and from Yahoo Finance / London Stock Exchange live data as at 26 June 2026. Projections are built from company-disclosed guidance and
A21: targets (organic growth 3-6%, operating margin path to >20% by FY2028, capex ~6% of sales), not third-party consensus. See Assumptions tab.

Sheet Assumptions
A1: Assumptions
A2: All hardcoded inputs (blue) live here. Nothing else in the workbook should contain a hardcoded driver.
A4: Operating assumptions - 2026E-2030E
B5: 2024A | C5: 2025A | D5: 2026E | E5: 2027E | F5: 2028E | G5: 2029E | H5: 2030E
A6: Revenue growth, % YoY | D6: 0.04 | E6: 0.045 | F6: 0.05 | G6: 0.05 | H6: 0.05
A7: Adjusted operating margin, % | D7: 0.182 | E7: 0.192 | F7: 0.202 | G7: 0.205 | H7: 0.208 | I7: Co. guidance: margin path 17.4% (2025A) to >20% by FY2028
A8: Capex, % of revenue | D8: 0.06 | E8: 0.06 | F8: 0.06 | G8: 0.06 | H8: 0.06 | I8: Co. guidance: capex ~6% of sales (Finance Review 2025)
A9: D&A, % of revenue | D9: 0.0694 | E9: 0.065 | F9: 0.063 | G9: 0.061 | H9: 0.06 | I9: 2026E approx £118m (2025A ~£108m + £10m co.-guided step-up); glides toward capex % thereafter
A10: Net working capital benefit / (use), £m | D10: -17 | E10: -17 | F10: -16 | G10: 0 | H10: 0 | I10: Co. target: structural NWC reduction of ~£50m by FY2028
A11: Net interest, £m | D11: 18.5 | E11: 17.5 | F11: 16.5 | G11: 15.5 | H11: 15 | I11: Simplifying glide path reflecting modest deleveraging; not a full debt schedule
A12: Tax rate on adjusted profit | B12: 0.26 | I12: Co. guidance: effective tax rate ~26% (Finance Review 2025)
A14: WACC / CAPM inputs
A15: Risk-free rate (UK 10Y gilt yield) | B15: 0.0475 | D15: Source: Trading Economics, 25 Jun 2026
A16: Beta (5Y monthly) | B16: 0.91 | D16: Source: Yahoo Finance, CRDA.L, 26 Jun 2026
A17: Equity market risk premium | B17: 0.05 | D17: Assumption: standard UK large-cap ERP
A18: Pre-tax cost of debt | B18: 0.06 | D18: Assumption: gilt yield + ~125bp investment-grade spread
A19: Terminal growth rate | B19: 0.02 | D19: Assumption: long-run UK nominal GDP proxy
A20: Cost of equity (CAPM) | B20: =B15+B16*B17 -> 0.093
A21: After-tax cost of debt | B21: =B18*(1-B12) -> 0.0444
A23: Capital structure & per-share
A24: Current share price, p | B24: 3107 | D24: Source: Yahoo Finance, live, 26 Jun 2026 (8:28 BST)
A25: Market capitalisation, GBP bn | B25: 4.33 | D25: Source: Yahoo Finance, live, 26 Jun 2026
A26: Diluted shares outstanding, m | B26: =B25*1000/(B24/100) -> 139.36273 | D26: Derived: market cap / price
A27: Net debt, 2025A, GBPm | B27: 523.8 | D27: Source: Croda Finance Review 2025
A28: Net debt, 2024A, GBPm | B28: 532.3 | D28: Source: Croda Finance Review 2025 (restated)
A29: Leverage, 2025A, x EBITDA | B29: 1.3 | D29: Source: Croda Finance Review 2025
A30: Leverage, 2024A, x EBITDA | B30: 1.4 | D30: Source: Croda Finance Review 2025

Sheet Income Statement
A1: Income Statement (GBPm unless stated)
A2: 2024A-2025A actuals from Croda's own results disclosures. 2026E-2030E driven entirely from the Assumptions tab.
B4: 2024A | C4: 2025A | D4: 2026E | E4: 2027E | F4: 2028E | G4: 2029E | H4: 2030E
A5: Revenue | B5: 1630 | C5: 1700 | D5: =C5*(1+Assumptions!D6) -> 1768 | E5: =D5*(1+Assumptions!E6) -> 1847.56 | F5: =E5*(1+Assumptions!F6) -> 1939.938 | G5: =F5*(1+Assumptions!G6) -> 2036.9349 | H5: =G5*(1+Assumptions!H6) -> 2138.7816 | I5: Sourced: stockanalysis.com / Croda results (FY24 ~£1.63bn, FY25 ~£1.70bn)
A6: % growth YoY | C6: =C5/B5-1 -> 0.042944785 | D6: =D5/C5-1 -> 0.04 | E6: =E5/D5-1 -> 0.045 | F6: =F5/E5-1 -> 0.05 | G6: =G5/F5-1 -> 0.05 | H6: =H5/G5-1 -> 0.05
A8: Adjusted operating margin, % | B8: 0.172 | C8: 0.174 | D8: =Assumptions!D7 -> 0.182 | E8: =Assumptions!E7 -> 0.192 | F8: =Assumptions!F7 -> 0.202 | G8: =Assumptions!G7 -> 0.205 | H8: =Assumptions!H7 -> 0.208 | I8: Sourced: Croda Annual Report 2025 / Finance Review 2025
A9: Adjusted Operating Profit (EBIT) | B9: =B5*B8 -> 280.36 | C9: =C5*C8 -> 295.8 | D9: =D5*D8 -> 321.776 | E9: =E5*E8 -> 354.73152 | F9: =F5*F8 -> 391.86748 | G9: =G5*G8 -> 417.57165 | H9: =H5*H8 -> 444.86658
A11: D&A | B11: =Assumptions!B28/Assumptions!B30-B9 -> 99.854286 | C11: =Assumptions!B27/Assumptions!B29-C9 -> 107.12308 | D11: =D5*Assumptions!D9 -> 122.6992 | E11: =E5*Assumptions!E9 -> 120.0914 | F11: =F5*Assumptions!F9 -> 122.21609 | G11: =G5*Assumptions!G9 -> 124.25303 | H11: =H5*Assumptions!H9 -> 128.3269 | I11: 2024A-2025A derived: (net debt / leverage) less EBIT - both co.-disclosed, avoids mixing in third-party EBITDA series
A12: EBITDA | B12: =B9+B11 -> 380.21429 | C12: =C9+C11 -> 402.92308 | D12: =D9+D11 -> 444.4752 | E12: =E9+E11 -> 474.82292 | F12: =F9+F11 -> 514.08357 | G12: =G9+G11 -> 541.82468 | H12: =H9+H11 -> 573.19348
A14: Net interest & other, net | B14: 18 | C14: 19 | D14: =Assumptions!D11 -> 18.5 | E14: =Assumptions!E11 -> 17.5 | F14: =Assumptions!F11 -> 16.5 | G14: =Assumptions!G11 -> 15.5 | H14: =Assumptions!H11 -> 15 | I14: 2025A derived: Adj. Operating Profit (£295m) less Adj. PBT (£276m), per Croda FY25 results
A15: Adjusted Profit Before Tax | B15: =B9-B14 -> 262.36 | C15: =C9-C14 -> 276.8 | D15: =D9-D14 -> 303.276 | E15: =E9-E14 -> 337.23152 | F15: =F9-F14 -> 375.36748 | G15: =G9-G14 -> 402.07165 | H15: =H9-H14 -> 429.86658
A16: Tax | B16: =B15*Assumptions!$B$12 -> 68.2136 | C16: =C15*Assumptions!$B$12 -> 71.968 | D16: =D15*Assumptions!$B$12 -> 78.85176 | E16: =E15*Assumptions!$B$12 -> 87.680195 | F16: =F15*Assumptions!$B$12 -> 97.595544 | G16: =G15*Assumptions!$B$12 -> 104.53863 | H16: =H15*Assumptions!$B$12 -> 111.76531
A17: Adjusted Net Income | B17: =B15-B16 -> 194.1464 | C17: =C15-C16 -> 204.832 | D17: =D15-D16 -> 224.42424 | E17: =E15-E16 -> 249.55132 | F17: =F15-F16 -> 277.77193 | G17: =G15-G16 -> 297.53302 | H17: =H15-H16 -> 318.10127
A19: Adjusted basic EPS, p | B19: =B17/Assumptions!$B$26*100 -> 139.31013 | C19: =C17/Assumptions!$B$26*100 -> 146.9776 | D19: =D17/Assumptions!$B$26*100 -> 161.03605 | E19: =E17/Assumptions!$B$26*100 -> 179.06604 | F19: =F17/Assumptions!$B$26*100 -> 199.3158 | G19: =G17/Assumptions!$B$26*100 -> 213.49541 | H19: =H17/Assumptions!$B$26*100 -> 228.25419 | I19: 2025A check: model approx 146p vs Croda-reported adjusted basic EPS of 146.2p
A20: Dividend per share, p | B20: 110 | C20: 111 | D20: 114 | E20: 118 | F20: 122 | G20: 128 | H20: 134 | I20: 2024A-2025A actual (110p, 111p). 2026E+ grown slower than EPS, gliding payout toward 40-50% policy band
A21: Payout ratio, % | B21: =B20/B19 -> 0.78960518 | C21: =C20/C19 -> 0.7552171 | D21: =D20/D19 -> 0.70791601 | E21: =E20/E19 -> 0.65897474 | F21: =F20/F19 -> 0.61209399 | G21: =G20/G19 -> 0.59954452 | H21: =H20/H19 -> 0.58706479

Sheet Cash Flow
A1: Cash Flow (GBPm)
A2: 2024A-2025A actuals shown as company-reported free cash flow. 2026E-2030E built bottom-up from the Income Statement and Assumptions.
B4: 2024A | C4: 2025A | D4: 2026E | E4: 2027E | F4: 2028E | G4: 2029E | H4: 2030E
A5: Adjusted Net Income | B5: ='Income Statement'!B17 -> 194.1464 | C5: ='Income Statement'!C17 -> 204.832 | D5: ='Income Statement'!D17 -> 224.42424 | E5: ='Income Statement'!E17 -> 249.55132 | F5: ='Income Statement'!F17 -> 277.77193 | G5: ='Income Statement'!G17 -> 297.53302 | H5: ='Income Statement'!H17 -> 318.10127
A6: + D&A | B6: ='Income Statement'!B11 -> 99.854286 | C6: ='Income Statement'!C11 -> 107.12308 | D6: ='Income Statement'!D11 -> 122.6992 | E6: ='Income Statement'!E11 -> 120.0914 | F6: ='Income Statement'!F11 -> 122.21609 | G6: ='Income Statement'!G11 -> 124.25303 | H6: ='Income Statement'!H11 -> 128.3269
A7: - Capex | B7: 137.9 | C7: 108.2 | D7: ='Income Statement'!D5*Assumptions!D8 -> 106.08 | E7: ='Income Statement'!E5*Assumptions!E8 -> 110.8536 | F7: ='Income Statement'!F5*Assumptions!F8 -> 116.39628 | G7: ='Income Statement'!G5*Assumptions!G8 -> 122.21609 | H7: ='Income Statement'!H5*Assumptions!H8 -> 128.3269 | I7: 2024A-2025A actual (Croda Finance Review 2025: £137.9m, £108.2m)
A8: +/- Net working capital | B8: 0 | C8: 0 | D8: =Assumptions!D10 -> -17 | E8: =Assumptions!E10 -> -17 | F8: =Assumptions!F10 -> -16 | G8: =Assumptions!G10 -> 0 | H8: =Assumptions!H10 -> 0 | I8: Not separately disclosed for 2024A-2025A; nil assumed (captured within reported FCF below)
A9: Free cash flow (model build-up) | B9: =B5+B6-B7+B8 -> 156.10069 | C9: =C5+C6-C7+C8 -> 203.75508 | D9: =D5+D6-D7+D8 -> 224.04344 | E9: =E5+E6-E7+E8 -> 241.78912 | F9: =F5+F6-F7+F8 -> 267.59175 | G9: =G5+G6-G7+G8 -> 299.56996 | H9: =H5+H6-H7+H8 -> 318.10127
A10: Memo: free cash flow as reported | B10: 169.6 | C10: 161.6 | I10: Source: Croda Finance Review 2025. Model build-up above uses the same inputs as the rest of this workbook for consistency.
A12: Dividends paid | B12: ='Income Statement'!B20/100*Assumptions!$B$26 -> 153.299 | C12: ='Income Statement'!C20/100*Assumptions!$B$26 -> 154.69263 | D12: ='Income Statement'!D20/100*Assumptions!$B$26 -> 158.87351 | E12: ='Income Statement'!E20/100*Assumptions!$B$26 -> 164.44802 | F12: ='Income Statement'!F20/100*Assumptions!$B$26 -> 170.02253 | G12: ='Income Statement'!G20/100*Assumptions!$B$26 -> 178.38429 | H12: ='Income Statement'!H20/100*Assumptions!$B$26 -> 186.74606
A13: Free cash flow after dividends | B13: =B9-B12 -> 2.8016835 | C13: =C9-C12 -> 49.062447 | D13: =D9-D12 -> 65.169929 | E13: =E9-E12 -> 77.341104 | F13: =F9-F12 -> 97.569216 | G13: =G9-G12 -> 121.18567 | H13: =H9-H12 -> 131.35521

Sheet Balance Sheet
A1: Balance Sheet (GBPm) - net debt roll-forward
A2: Scope limited to net debt, the item that drives the DCF bridge. A full statutory balance sheet needs receivables/payables/PP&E detail not available from public disclosure alone.
B4: 2024A | C4: 2025A | D4: 2026E | E4: 2027E | F4: 2028E | G4: 2029E | H4: 2030E
A5: Net debt, opening | B5: n/a | C5: =B7 -> 532.3 | D5: =C7 -> 523.8 | E5: =D7 -> 458.63007 | F5: =E7 -> 381.28897 | G5: =F7 -> 283.71975 | H5: =G7 -> 162.53409
A6: (Free cash flow after dividends) | B6: n/a | C6: ='Cash Flow'!C13 -> 49.062447 | D6: ='Cash Flow'!D13 -> 65.169929 | E6: ='Cash Flow'!E13 -> 77.341104 | F6: ='Cash Flow'!F13 -> 97.569216 | G6: ='Cash Flow'!G13 -> 121.18567 | H6: ='Cash Flow'!H13 -> 131.35521
A7: Net debt, closing | B7: 532.3 | C7: 523.8 | D7: =D5-D6 -> 458.63007 | E7: =E5-E6 -> 381.28897 | F7: =F5-F6 -> 283.71975 | G7: =G5-G6 -> 162.53409 | H7: =H5-H6 -> 31.178872 | I7: 2024A-2025A actual (Croda Finance Review 2025); 2026E+ = opening less FCF after dividends
A9: Leverage check, x EBITDA | B9: =B7/'Income Statement'!B12 -> 1.4 | C9: =C7/'Income Statement'!C12 -> 1.3 | D9: =D7/'Income Statement'!D12 -> 1.0318463 | E9: =E7/'Income Statement'!E12 -> 0.80301298 | F9: =F7/'Income Statement'!F12 -> 0.55189422 | G9: =G7/'Income Statement'!G12 -> 0.29997542 | H9: =H7/'Income Statement'!H12 -> 0.054395021 | I9: Cross-check vs. Croda's own 1.3x (2025A) / 1.4x (2024A) disclosed leverage

Sheet DCF
A1: Discounted Cash Flow
A2: Unlevered FCFF discounted at WACC. 2026E-2030E explicit forecast, Gordon growth terminal value.
B4: 2026E | C4: 2027E | D4: 2028E | E4: 2029E | F4: 2030E
A5: Adjusted Operating Profit (EBIT) | B5: ='Income Statement'!D9 -> 321.776 | C5: ='Income Statement'!E9 -> 354.73152 | D5: ='Income Statement'!F9 -> 391.86748 | E5: ='Income Statement'!G9 -> 417.57165 | F5: ='Income Statement'!H9 -> 444.86658
A6: Tax on EBIT | B6: =B5*Assumptions!$B$12 -> 83.66176 | C6: =C5*Assumptions!$B$12 -> 92.230195 | D6: =D5*Assumptions!$B$12 -> 101.88554 | E6: =E5*Assumptions!$B$12 -> 108.56863 | F6: =F5*Assumptions!$B$12 -> 115.66531
A7: NOPAT | B7: =B5-B6 -> 238.11424 | C7: =C5-C6 -> 262.50132 | D7: =D5-D6 -> 289.98193 | E7: =E5-E6 -> 309.00302 | F7: =F5-F6 -> 329.20127
A8: + D&A | B8: ='Income Statement'!D11 -> 122.6992 | C8: ='Income Statement'!E11 -> 120.0914 | D8: ='Income Statement'!F11 -> 122.21609 | E8: ='Income Statement'!G11 -> 124.25303 | F8: ='Income Statement'!H11 -> 128.3269
A9: - Capex | B9: ='Cash Flow'!D7 -> 106.08 | C9: ='Cash Flow'!E7 -> 110.8536 | D9: ='Cash Flow'!F7 -> 116.39628 | E9: ='Cash Flow'!G7 -> 122.21609 | F9: ='Cash Flow'!H7 -> 128.3269
A10: +/- Net working capital | B10: =Assumptions!D10 -> -17 | C10: =Assumptions!E10 -> -17 | D10: =Assumptions!F10 -> -16 | E10: =Assumptions!G10 -> 0 | F10: =Assumptions!H10 -> 0
A11: Unlevered FCFF | B11: =B7+B8-B9+B10 -> 237.73344 | C11: =C7+C8-C9+C10 -> 254.73912 | D11: =D7+D8-D9+D10 -> 279.80175 | E11: =E7+E8-E9+E10 -> 311.03996 | F11: =F7+F8-F9+F10 -> 329.20127
A13: WACC | B13: =(Assumptions!B25*1000/(Assumptions!B25*1000+Assumptions!B27))*Assumptions!B20+(Assumptions!B27/(Assumptions!B25*1000+Assumptions!B27))*Assumptions!B21 -> 0.087755309 | D13: WACC = (E/V) x Cost of equity + (D/V) x After-tax cost of debt
A14: Terminal growth rate | B14: =Assumptions!B19 -> 0.02
A16: Discount period | B16: 1 | C16: 2 | D16: 3 | E16: 4 | F16: 5
A17: Discount factor | B17: =1/(1+$B$13)^B16 -> 0.9193244 | C17: =1/(1+$B$13)^C16 -> 0.84515736 | D17: =1/(1+$B$13)^D16 -> 0.77697378 | E17: =1/(1+$B$13)^E16 -> 0.71429096 | F17: =1/(1+$B$13)^F16 -> 0.65666511
A18: PV of FCFF | B18: =B11*B17 -> 218.55415 | C18: =C11*C17 -> 215.29465 | D18: =D11*D17 -> 217.39862 | E18: =E11*E17 -> 222.17303 | F18: =F11*F17 -> 216.17499
A20: Sum of PV, explicit period | B20: =SUM(B18:F18) -> 1089.5954
A21: Terminal value (at end of 2030E) | B21: =F11*(1+B14)/(B13-B14) -> 4955.8522
A22: PV of terminal value | B22: =B21*F17 -> 3254.3352
A23: Enterprise Value | B23: =B20+B22 -> 4343.9306
A24: Less: Net debt (2025A) | B24: =Assumptions!B27 -> 523.8
A25: Equity Value | B25: =B23-B24 -> 3820.1306
A26: Diluted shares, m | B26: =Assumptions!B26 -> 139.36273
A27: Implied value per share | B27: =B25/B26*100 -> 2741.1422
A28: vs. current share price | B28: =B27/Assumptions!B24-1 -> -0.11775274
A30: Sensitivity: implied value per share (p)
A31: Rows: WACC. Columns: terminal growth rate. Each cell recomputes the full DCF at that WACC / g combination.
B32: Terminal growth -> | C32: =$B$14+(-0.01) -> 0.01 | D32: =$B$14+(-0.005) -> 0.015 | E32: =$B$14+(0) -> 0.02 | F32: =$B$14+(0.005) -> 0.025 | G32: =$B$14+(0.01) -> 0.03
B33: =$B$13+(-0.01) -> 0.077755309 | C33: =((B11/(1+$B33)^1+C11/(1+$B33)^2+D11/(1+$B33)^3+E11/(1+$B33)^4+F11/(1+$B33)^5+(F11*(1+C$32)/($B33-C$32))/(1+$B33)^5)-B24)/B26*100 -> 2849.5784 | D33: =((B11/(1+$B33)^1+C11/(1+$B33)^2+D11/(1+$B33)^3+E11/(1+$B33)^4+F11/(1+$B33)^5+(F11*(1+D$32)/($B33-D$32))/(1+$B33)^5)-B24)/B26*100 -> 3055.4566 | E33: =((B11/(1+$B33)^1+C11/(1+$B33)^2+D11/(1+$B33)^3+E11/(1+$B33)^4+F11/(1+$B33)^5+(F11*(1+E$32)/($B33-E$32))/(1+$B33)^5)-B24)/B26*100 -> 3296.9814 | F33: =((B11/(1+$B33)^1+C11/(1+$B33)^2+D11/(1+$B33)^3+E11/(1+$B33)^4+F11/(1+$B33)^5+(F11*(1+F$32)/($B33-F$32))/(1+$B33)^5)-B24)/B26*100 -> 3584.2883 | G33: =((B11/(1+$B33)^1+C11/(1+$B33)^2+D11/(1+$B33)^3+E11/(1+$B33)^4+F11/(1+$B33)^5+(F11*(1+G$32)/($B33-G$32))/(1+$B33)^5)-B24)/B26*100 -> 3931.7576
B34: =$B$13+(-0.005) -> 0.082755309 | C34: =((B11/(1+$B34)^1+C11/(1+$B34)^2+D11/(1+$B34)^3+E11/(1+$B34)^4+F11/(1+$B34)^5+(F11*(1+C$32)/($B34-C$32))/(1+$B34)^5)-B24)/B26*100 -> 2620.4278 | D34: =((B11/(1+$B34)^1+C11/(1+$B34)^2+D11/(1+$B34)^3+E11/(1+$B34)^4+F11/(1+$B34)^5+(F11*(1+D$32)/($B34-D$32))/(1+$B34)^5)-B24)/B26*100 -> 2794.7512 | E34: =((B11/(1+$B34)^1+C11/(1+$B34)^2+D11/(1+$B34)^3+E11/(1+$B34)^4+F11/(1+$B34)^5+(F11*(1+E$32)/($B34-E$32))/(1+$B34)^5)-B24)/B26*100 -> 2996.8528 | F34: =((B11/(1+$B34)^1+C11/(1+$B34)^2+D11/(1+$B34)^3+E11/(1+$B34)^4+F11/(1+$B34)^5+(F11*(1+F$32)/($B34-F$32))/(1+$B34)^5)-B24)/B26*100 -> 3233.9471 | G34: =((B11/(1+$B34)^1+C11/(1+$B34)^2+D11/(1+$B34)^3+E11/(1+$B34)^4+F11/(1+$B34)^5+(F11*(1+G$32)/($B34-G$32))/(1+$B34)^5)-B24)/B26*100 -> 3515.9837
B35: =$B$13+(0) -> 0.087755309 | C35: =((B11/(1+$B35)^1+C11/(1+$B35)^2+D11/(1+$B35)^3+E11/(1+$B35)^4+F11/(1+$B35)^5+(F11*(1+C$32)/($B35-C$32))/(1+$B35)^5)-B24)/B26*100 -> 2420.872 | D35: =((B11/(1+$B35)^1+C11/(1+$B35)^2+D11/(1+$B35)^3+E11/(1+$B35)^4+F11/(1+$B35)^5+(F11*(1+D$32)/($B35-D$32))/(1+$B35)^5)-B24)/B26*100 -> 2570.0021 | E35: =((B11/(1+$B35)^1+C11/(1+$B35)^2+D11/(1+$B35)^3+E11/(1+$B35)^4+F11/(1+$B35)^5+(F11*(1+E$32)/($B35-E$32))/(1+$B35)^5)-B24)/B26*100 -> 2741.1422 | F35: =((B11/(1+$B35)^1+C11/(1+$B35)^2+D11/(1+$B35)^3+E11/(1+$B35)^4+F11/(1+$B35)^5+(F11*(1+F$32)/($B35-F$32))/(1+$B35)^5)-B24)/B26*100 -> 2939.5535 | G35: =((B11/(1+$B35)^1+C11/(1+$B35)^2+D11/(1+$B35)^3+E11/(1+$B35)^4+F11/(1+$B35)^5+(F11*(1+G$32)/($B35-G$32))/(1+$B35)^5)-B24)/B26*100 -> 3172.3184
B36: =$B$13+(0.005) -> 0.092755309 | C36: =((B11/(1+$B36)^1+C11/(1+$B36)^2+D11/(1+$B36)^3+E11/(1+$B36)^4+F11/(1+$B36)^5+(F11*(1+C$32)/($B36-C$32))/(1+$B36)^5)-B24)/B26*100 -> 2245.5439 | D36: =((B11/(1+$B36)^1+C11/(1+$B36)^2+D11/(1+$B36)^3+E11/(1+$B36)^4+F11/(1+$B36)^5+(F11*(1+D$32)/($B36-D$32))/(1+$B36)^5)-B24)/B26*100 -> 2374.2702 | E36: =((B11/(1+$B36)^1+C11/(1+$B36)^2+D11/(1+$B36)^3+E11/(1+$B36)^4+F11/(1+$B36)^5+(F11*(1+E$32)/($B36-E$32))/(1+$B36)^5)-B24)/B26*100 -> 2520.6895 | F36: =((B11/(1+$B36)^1+C11/(1+$B36)^2+D11/(1+$B36)^3+E11/(1+$B36)^4+F11/(1+$B36)^5+(F11*(1+F$32)/($B36-F$32))/(1+$B36)^5)-B24)/B26*100 -> 2688.7189 | G36: =((B11/(1+$B36)^1+C11/(1+$B36)^2+D11/(1+$B36)^3+E11/(1+$B36)^4+F11/(1+$B36)^5+(F11*(1+G$32)/($B36-G$32))/(1+$B36)^5)-B24)/B26*100 -> 2883.5236
B37: =$B$13+(0.01) -> 0.097755309 | C37: =((B11/(1+$B37)^1+C11/(1+$B37)^2+D11/(1+$B37)^3+E11/(1+$B37)^4+F11/(1+$B37)^5+(F11*(1+C$32)/($B37-C$32))/(1+$B37)^5)-B24)/B26*100 -> 2090.2999 | D37: =((B11/(1+$B37)^1+C11/(1+$B37)^2+D11/(1+$B37)^3+E11/(1+$B37)^4+F11/(1+$B37)^5+(F11*(1+D$32)/($B37-D$32))/(1+$B37)^5)-B24)/B26*100 -> 2202.2936 | E37: =((B11/(1+$B37)^1+C11/(1+$B37)^2+D11/(1+$B37)^3+E11/(1+$B37)^4+F11/(1+$B37)^5+(F11*(1+E$32)/($B37-E$32))/(1+$B37)^5)-B24)/B26*100 -> 2328.6906 | F37: =((B11/(1+$B37)^1+C11/(1+$B37)^2+D11/(1+$B37)^3+E11/(1+$B37)^4+F11/(1+$B37)^5+(F11*(1+F$32)/($B37-F$32))/(1+$B37)^5)-B24)/B26*100 -> 2472.4605 | G37: =((B11/(1+$B37)^1+C11/(1+$B37)^2+D11/(1+$B37)^3+E11/(1+$B37)^4+F11/(1+$B37)^5+(F11*(1+G$32)/($B37-G$32))/(1+$B37)^5)-B24)/B26*100 -> 2637.4493

Sheet Comps
A1: Trading Comparables
A2: Croda against three specialty ingredients peers. FX: $1.32/£, €1.17/£ (Croda's own disclosed average 2025 rates), CHF1.15/£ (assumption).
A4: Company | B4: Mkt Cap (£bn) | C4: Net Debt (£bn) | D4: EV (£bn) | E4: Revenue (£bn) | F4: EBITDA (£bn) | G4: EV / Revenue | H4: EV / EBITDA | I4: Adj. EPS (p) | J4: P / E (adj.)
A5: Croda International | B5: =Assumptions!B25 -> 4.33 | C5: =Assumptions!B27/1000 -> 0.5238 | D5: =B5+C5 -> 4.8538 | E5: ='Income Statement'!C5/1000 -> 1.7 | F5: ='Income Statement'!C12/1000 -> 0.40292308 | G5: =D5/E5 -> 2.8551765 | H5: =D5/F5 -> 12.046468 | I5: ='Income Statement'!C19 -> 146.9776 | J5: =Assumptions!B24/I5 -> 21.139275
A6: DSM-Firmenich | B6: 12.88 | C6: 3.03 | D6: =B6+C6 -> 15.91 | E6: 10.61 | F6: =D6/8.2 -> 1.9402439 | G6: =D6/E6 -> 1.4995287 | H6: 8.2 | I6: n/a | J6: 21.8
A7: Symrise | B7: 10.08 | C7: n/a | D7: n/a | E7: 4.21 | F7: n/a | G7: n/a | H7: n/a | I7: n/a | J7: 36
A8: Givaudan | B8: 26.09 | C8: n/a | D8: n/a | E8: 6.81 | F8: n/a | G8: n/a | H8: n/a | I8: n/a | J8: 20.6
A9: Sources: DSM-Firmenich — multiples.vc, Mar 2026. Symrise — Investing.com / PitchBook, Apr-Jun 2026 (P/E range 32x-44x across sources; 36x used as representative). Givaudan — PitchBook / Ad-Hoc-News, Jun 2026, P/E derived from CHF price and USD EPS.
A11: Average peer P/E (ex-Croda) | J11: =AVERAGE(J6,J7,J8) -> 26.133333
A12: Implied Croda value per share, peer P/E basis | J12: =I5*J11 -> 3841.0147
A13: Implied Croda value per share, EV/EBITDA basis (DSM-Firmenich only) | J13: =((H6*F5)-Assumptions!B27/1000)*1000/Assumptions!B26*100 -> 1994.9159
A15: EV/EBITDA cross-check limited to one peer with cleanly disclosed net debt (DSM-Firmenich); P/E is the more reliable cross-peer comparison
A16: here given thinner net-debt disclosure for Symrise and Givaudan from public aggregators.

Sheet Summary
A1: Valuation Summary
A2: Where the DCF, the comps, the 52-week range, and the Street currently disagree on Croda.
A4: Method | B4: Low (p) | C4: High (p) | E4: Low (invisible base) | F4: Range (visible)
A5: 52-week trading range | B5: 2427 | C5: 3312 | E5: =B5 -> 2427 | F5: =C5-B5 -> 885
A6: DCF (WACC / growth sensitivity) | B6: =MIN(DCF!C33:G37) -> 2090.2999 | C6: =MAX(DCF!C33:G37) -> 3931.7576 | E6: =B6 -> 2090.2999 | F6: =C6-B6 -> 1841.4576
A7: Comps (peer P/E range applied to Croda EPS) | B7: =Comps!I5*MIN(Comps!J6,Comps!J7,Comps!J8) -> 3027.7386 | C7: =Comps!I5*MAX(Comps!J6,Comps!J7,Comps!J8) -> 5291.1937 | E7: =B7 -> 3027.7386 | F7: =C7-B7 -> 2263.4551
A8: Street analyst targets (low-high) | B8: 2865 | C8: 5200 | E8: =B8 -> 2865 | F8: =C8-B8 -> 2335
A9: Current price (marker) | B9: =Assumptions!B24 -> 3107 | C9: =Assumptions!B24+25 -> 3132 | E9: =B9 -> 3107 | F9: =C9-B9 -> 25
A10: Reading this
A11: The DCF base case (2,741p) actually sits slightly below the current price, model conservatism, not a data error,
A12: driven by an 8.8% WACC and a 2% terminal growth rate. The wide sensitivity range (2,090p-3,932p) comfortably brackets
A13: the current price either way. Comps and Street analyst targets both point higher.
A14: The honest read: this is not a screaming bargain on a bottom-up DCF. The case for Croda rests more on the qualitative
A15: thesis, lipid platform durability and the Consumer Care recovery, than on the DCF alone, which is exactly why the
A16: equity note leads with the narrative rather than a single price target.
